underscorec/__init__.py
underscorec/underscorec.cpp
underscorec/underscorec.cpython-310-darwin.so
underscorec/underscorec_numpy.cpp
underscorec/underscorec_numpy.h
underscorec/underscorec_torch.cpp
underscorec/underscorec_torch.h
underscorec/underscorec_types.h
underscorec-0.1.0.dist-info/METADATA
underscorec-0.1.0.dist-info/WHEEL
underscorec-0.1.0.dist-info/top_level.txt
underscorec-0.1.0.dist-info/RECORD
