Metadata-Version: 2.4
Name: underscorec
Version: 0.1.0
Summary: C-based functional programming library with __ syntax for Python
Requires-Python: >=3.10
Requires-Dist: numpy>=2.2.6
Requires-Dist: pandas>=2.3.1
Requires-Dist: torch>=2.0.0
